lib/__init__.py
lib/compress/__init__.py
lib/compress/compress_sql.py
lib/config/__init__.py
lib/config/parse_config.py
lib/expand/__init__.py
lib/expand/expand_sql.py
test/__init__.py
test/compress/__init__.py
test/compress/test_compress_sql.py
test/config/__init__.py
test/config/test_parse_config.py
test/expand/__init__.py
test/expand/test_expand_sql.py
sqlcomp-0.1.0.dist-info/LICENSE
sqlcomp-0.1.0.dist-info/METADATA
sqlcomp-0.1.0.dist-info/WHEEL
sqlcomp-0.1.0.dist-info/top_level.txt
sqlcomp-0.1.0.dist-info/RECORD
