Metadata-Version: 2.1
Name: sqlcomp
Version: 0.1.0
Summary: A library for edge cases where shortening SQL is helpful.
Home-page: https://github.com/Romulus10/sqlcomp
Author: Romulus10
Author-email: romulus108@protonmail.com
License: GPL v3
Platform: UNKNOWN
